pyAMARES/__init__.py
pyAMARES/examples/example_human_brain_31P_7T.csv
pyAMARES/examples/fid.txt
pyAMARES/examples/human_brain_31P_7T.csv
pyAMARES/examples/simple_example.csv
pyAMARES/examples/simple_example.html
pyAMARES/examples/simple_example.svg
pyAMARES/examples/simple_example_html.jpeg
pyAMARES/fileio/__init__.py
pyAMARES/fileio/readfidall.py
pyAMARES/fileio/readmat.py
pyAMARES/fileio/readnifti.py
pyAMARES/kernel/PriorKnowledge.py
pyAMARES/kernel/__init__.py
pyAMARES/kernel/fid.py
pyAMARES/kernel/lmfit.py
pyAMARES/kernel/objective_func.py
pyAMARES/libs/MPFIR.py
pyAMARES/libs/__init__.py
pyAMARES/libs/hlsvd.py
pyAMARES/libs/logger.py
pyAMARES/script/__init__.py
pyAMARES/script/amaresfit.py
pyAMARES/util/__init__.py
pyAMARES/util/crlb.py
pyAMARES/util/hsvd.py
pyAMARES/util/misc.py
pyAMARES/util/multiprocessing.py
pyAMARES/util/report.py
pyAMARES/util/visualization.py
tests/__init__.py
tests/test_notebooks.py
pyamares-0.3.28.dist-info/LICENSE.txt
pyamares-0.3.28.dist-info/METADATA
pyamares-0.3.28.dist-info/WHEEL
pyamares-0.3.28.dist-info/entry_points.txt
pyamares-0.3.28.dist-info/top_level.txt
pyamares-0.3.28.dist-info/RECORD
