Metadata-Version: 2.1
Name: pyAMARES
Version: 0.3.28
Summary: PyAMARES, an Open-Source Python Library for Fitting Magnetic Resonance Spectroscopy Data
Home-page: https://github.com/hawkMRS/pyAMARES
Author: Jia Xu, MR Research Facility, University of Iowa
Author-email: jia-xu-1@uiowa.edu
Classifier: Programming Language :: Python :: 3
Classifier: Programming Language :: Python :: 3.6
Classifier: Programming Language :: Python :: 3.7
Classifier: Programming Language :: Python :: 3.8
Classifier: Programming Language :: Python :: 3.9
Classifier: Programming Language :: Python :: 3.10
Classifier: Programming Language :: Python :: 3.11
Classifier: Programming Language :: Python :: 3.12
Classifier: Topic :: Scientific/Engineering
Classifier: License :: OSI Approved :: BSD License
Classifier: Operating System :: OS Independent
Requires-Python: >=3.6
License-File: LICENSE.txt
Requires-Dist: pandas>=1.1.0
Requires-Dist: matplotlib>=3.1.3
Requires-Dist: lmfit
Requires-Dist: numpy>=1.18.1
Requires-Dist: scipy>=1.2.1
Requires-Dist: sympy
Requires-Dist: nmrglue
Requires-Dist: xlrd
Requires-Dist: jinja2
Requires-Dist: tqdm
Requires-Dist: mat73
Requires-Dist: ipython
Requires-Dist: ipykernel
Requires-Dist: requests
Requires-Dist: hlsvdpro>=2.0.0
Requires-Dist: ipywidgets<8.0.0,>=7.6.0; python_version < "3.11"
Requires-Dist: ipywidgets>=8.0.0; python_version >= "3.11"
Provides-Extra: dev
Requires-Dist: ipykernel; extra == "dev"
Requires-Dist: notebook; extra == "dev"
Requires-Dist: sphinx; extra == "dev"
Requires-Dist: nbsphinx; extra == "dev"
Requires-Dist: sphinx-tabs; extra == "dev"
Requires-Dist: sphinx-rtd-theme; extra == "dev"
Requires-Dist: Pygments; extra == "dev"
Requires-Dist: ipywidgets; extra == "dev"
Requires-Dist: ruff; extra == "dev"
Requires-Dist: pre-commit; extra == "dev"
Requires-Dist: pytest; extra == "dev"
Provides-Extra: docs
Requires-Dist: sphinx; extra == "docs"
Requires-Dist: nbsphinx; extra == "docs"
Requires-Dist: sphinx-tabs; extra == "docs"
Requires-Dist: sphinx-rtd-theme; extra == "docs"
Requires-Dist: Pygments; extra == "docs"
Requires-Dist: ipywidgets; extra == "docs"
Provides-Extra: jupyter
Requires-Dist: ipykernel; extra == "jupyter"
Requires-Dist: notebook; extra == "jupyter"
Provides-Extra: ruff
Requires-Dist: ruff; extra == "ruff"
Requires-Dist: pre-commit; extra == "ruff"
Requires-Dist: pytest; extra == "ruff"
